certora_cli/__init__.py
certora_cli/certoraEqCheck.py
certora_cli/certoraMutate.py
certora_cli/certoraRun.py
certora_cli/EVMVerifier/__init__.py
certora_cli/EVMVerifier/certoraBuild.py
certora_cli/EVMVerifier/certoraCloudIO.py
certora_cli/EVMVerifier/certoraCollectRunMetadata.py
certora_cli/EVMVerifier/certoraConfigIO.py
certora_cli/EVMVerifier/certoraContext.py
certora_cli/EVMVerifier/certoraContextAttribute.py
certora_cli/EVMVerifier/certoraContextClass.py
certora_cli/EVMVerifier/certoraContextValidator.py
certora_cli/EVMVerifier/certoraExtensionInfo.py
certora_cli/EVMVerifier/certoraJobList.py
certora_cli/EVMVerifier/certoraNodeFilters.py
certora_cli/EVMVerifier/certoraType.py
certora_cli/EVMVerifier/certoraValidateFuncs.py
certora_cli/EVMVerifier/Compiler/CompilerCollector.py
certora_cli/EVMVerifier/Compiler/CompilerCollectorFactory.py
certora_cli/EVMVerifier/Compiler/CompilerCollectorSol.py
certora_cli/EVMVerifier/Compiler/CompilerCollectorVy.py
certora_cli/Shared/__init__.py
certora_cli/Shared/certoraLogging.py
certora_cli/Shared/certoraTester.py
certora_cli/Shared/certoraUtils.py
release_bins/__init__.py
release_bins/certora_jars/MutationTest.jar
release_bins/certora_jars/Typechecker.3.6.5.jar
release_bins/certora_jars/Typechecker.jar
release_bins/certora_jars/__init__.py
scripts/EquivalenceCheck/Eq_default.conf
scripts/EquivalenceCheck/Eq_mc_template.spec
scripts/EquivalenceCheck/Eq_sanity.conf
scripts/EquivalenceCheck/Eq_template.spec
scripts/EquivalenceCheck/equivCheck.py
scripts/EquivalenceCheck/sanity.spec
certora_cli_alpha_uri_eradicate_certora_dir-20230801.15.42.608313.dist-info/LICENSE
certora_cli_alpha_uri_eradicate_certora_dir-20230801.15.42.608313.dist-info/METADATA
certora_cli_alpha_uri_eradicate_certora_dir-20230801.15.42.608313.dist-info/WHEEL
certora_cli_alpha_uri_eradicate_certora_dir-20230801.15.42.608313.dist-info/entry_points.txt
certora_cli_alpha_uri_eradicate_certora_dir-20230801.15.42.608313.dist-info/top_level.txt
certora_cli_alpha_uri_eradicate_certora_dir-20230801.15.42.608313.dist-info/RECORD
