Metadata-Version: 2.1
Name: certora-cli-alpha-uri-eradicate-certora-dir
Version: 20230801.15.42.608313
Summary: Runner for the Certora Prover
Home-page: https://pypi.org/project/certora-cli-alpha-uri-eradicate_certora_dir
Author: Certora
Author-email: support@certora.com
Classifier: Programming Language :: Python :: 3
Classifier: License :: OSI Approved :: MIT License
Classifier: Operating System :: OS Independent
Requires-Python: >=3.8
License-File: LICENSE
